eilib/__init__.py
eilib/errors.py
eilib/database/__init__.py
eilib/database/abstract.py
eilib/database/acks.py
eilib/database/basic_types.py
eilib/database/codegen.py
eilib/database/errors.py
eilib/database/helpers.py
eilib/database/items.py
eilib/database/levers.py
eilib/database/perks.py
eilib/database/prints.py
eilib/database/quests.py
eilib/database/schemas.py
eilib/database/spells.py
eilib/database/units.py
eilib/database/tests/__init__.py
eilib/database/tests/test_codegen.py
eilib/database/tests/test_saveload.py
eilib-0.0.1.dist-info/LICENSE.txt
eilib-0.0.1.dist-info/METADATA
eilib-0.0.1.dist-info/WHEEL
eilib-0.0.1.dist-info/top_level.txt
eilib-0.0.1.dist-info/RECORD
