Metadata-Version: 2.1
Name: eilib
Version: 0.0.1
Summary: Library to work with Evil Islands binary formats
Home-page: https://github.com/koteyur/eilib
Author: Yury Kotov
Author-email: koteyur@gmail.com
License: UNKNOWN
Platform: UNKNOWN
Classifier: Programming Language :: Python :: 3
Classifier: License :: OSI Approved :: MIT License
Classifier: Operating System :: OS Independent
Requires-Python: >=3.6
